webfuse/__init__.py
webfuse/async_client.py
webfuse/async_session.py
webfuse/client.py
webfuse/exceptions.py
webfuse/session.py
webfuse-0.0.1.dist-info/METADATA
webfuse-0.0.1.dist-info/WHEEL
webfuse-0.0.1.dist-info/RECORD
