Metadata-Version: 2.4
Name: webfuse
Version: 0.0.1
Summary: Python SDK for automating browser sessions via Webfuse
Project-URL: Homepage, https://webfuse.com
Project-URL: Documentation, https://docs.webfuse.com/sdk/python
Project-URL: Repository, https://github.com/webfuse/webfuse-python
Project-URL: Changelog, https://github.com/webfuse/webfuse-python/blob/main/CHANGELOG.md
Author-email: Surfly <support@surfly.com>
License-Expression: MIT
Keywords: automation,browser,rpc,scraping,testing,web,webfuse
Classifier: Development Status :: 2 - Pre-Alpha
Classifier: Intended Audience :: Developers
Classifier: License :: OSI Approved :: MIT License
Classifier: Operating System :: OS Independent
Classifier: Programming Language :: Python :: 3
Classifier: Programming Language :: Python :: 3.8
Classifier: Programming Language :: Python :: 3.9
Classifier: Programming Language :: Python :: 3.10
Classifier: Programming Language :: Python :: 3.11
Classifier: Programming Language :: Python :: 3.12
Classifier: Topic :: Internet :: WWW/HTTP :: Browsers
Classifier: Topic :: Software Development :: Libraries :: Python Modules
Classifier: Topic :: Software Development :: Testing
Classifier: Typing :: Typed
Requires-Python: >=3.8
Requires-Dist: httpx>=0.24.0
Provides-Extra: dev
Requires-Dist: black>=23.0.0; extra == 'dev'
Requires-Dist: mypy>=1.0.0; extra == 'dev'
Requires-Dist: pytest-asyncio>=0.21.0; extra == 'dev'
Requires-Dist: pytest>=7.0.0; extra == 'dev'
Requires-Dist: ruff>=0.1.0; extra == 'dev'
